{
  "metadata": {
    "exam_type": "110",
    "level": "四等",
    "subject": "國境執法概要與刑事法概要（包括刑法概要與刑事訴訟法概要）",
    "exam_time": "1小時30分 座號：",
    "code": "80140",
    "exam_name": "移民行政人員特種考試",
    "year": 110
  },
  "notes": [
    "※注意：禁止使用電子計算器。",
    "不必抄題，作答時請將試題題號及答案依照順序寫在申論試卷上，於本試題上作答者，不予計分。",
    "請以藍、黑色鋼筆或原子筆在申論試卷上作答。",
    "本科目除專門名詞或數理公式外，應使用本國文字作答。",
    "本測驗試題為單一選擇題，請選出一個正確或最適當的答案，複選作答者，該題不予計分。",
    "共25題，每題2分，須用2B鉛筆在試卡上依題號清楚劃記，於本試題或申論試卷上作答者，不予計分。"
  ],
  "sections": [
    "甲、申論題",
    "乙、測驗題"
  ],
  "questions": [
    {
      "number": "一",
      "type": "essay",
      "stem": "隨著新冠肺炎在全球爆發,各國封鎖邊境、航班大減,有幾位臺灣旅外\n國民因為買不到機票,遂集資購買一艘馬來西亞遊艇自行從東南亞航行\n返臺,逕入興達港,卻無法登陸,又被迫轉往安平港,但依然無法登岸\n入境。請問他們要返臺依法應做什麼動作?(15 分)面臨什麼罰則?\n(10 分)",
      "section": "甲、申論題"
    },
    {
      "number": "二",
      "type": "essay",
      "stem": "某日甲佯裝顧客,趁手機行老闆乙不注意,拿走放在櫃臺上的新手機,\n轉身就跑。乙趕緊追出店外,一邊追趕甲,一邊大聲呼救。路人丙見狀\n馬上撲向甲,卻被甲順勢絆倒在地,全身多處擦傷。甲趁亂騎著自己的\n摩托車逃離現場。沒想到在幾公里遠外的路口被巡邏員警丁依通報之車\n牌尋獲,丁當場將甲逮捕並告知刑事訴訟法第 95 條之權利事項,接著以\n手銬將甲扣在警車後座,確認甲無法反抗後,再打開摩托車行李箱,從\n中查扣贓物手機一支及一小包安非他命。請問:\n甲的刑事責任為何?(無須討論毒品相關犯罪)(12 分)\n丁之逮捕是否合法?(8 分)\n所查扣之安非他命能否作為認定甲成立持有二級毒品罪之證據?\n(5 分)",
      "section": "甲、申論題"
    },
    {
      "number": 1,
      "type": "choice",
      "stem": "有關國境安全檢查,下列敘述何者正確?",
      "section": "乙、測驗題",
      "options": {
        "A": "警察及海岸巡防機關人員須取得法院核發之搜索票始得進行國境安全檢查",
        "B": "國境安全檢查之執行機關除警察及海岸巡防機關外,尚包含內政部移民署",
        "C": "為確保國家安全,對於執法人員所進行之國境安全檢查不得提起行政救濟",
        "D": "無正當理由拒絕或逃避國境安全檢查者,依法將有刑事責任而受制裁"
      },
      "answer": "D"
    },
    {
      "number": 2,
      "type": "choice",
      "stem": "依據國家安全法與其施行細則有關國境安全檢查之規定,下列敘述何者錯誤?",
      "section": "乙、測驗題",
      "options": {
        "A": "國境安全檢查包含身體搜索,若搜索婦女之身體應命婦女行之",
        "B": "為確保返國權利,我國國民入境時得免受相關國境安全檢查",
        "C": "旅客與機員之手提行李,應由其自行開啟接受檢查",
        "D": "過境之旅客非經檢查許可,不得會晤境內人員及授受物品"
      },
      "answer": "B"
    },
    {
      "number": 3,
      "type": "choice",
      "stem": "有關管制區之指定與限制,依國家安全法及其施行細則規定,下列敘述何者正確?",
      "section": "乙、測驗題",
      "options": {
        "A": "國防部得會同法務部指定若干地區劃為管制區,並依法予以公告",
        "B": "人民入出海洋管制區,應向該地管轄之警察機關申請許可",
        "C": "管制區為軍事所必需者,得實施限建、禁建,並由國防部會同內政部及有關機關劃定範圍",
        "D": "管制區是為保障國境安全,因此僅限於海岸及重要軍事設施地區,不包含國家領域內之山地地區"
      },
      "answer": "C"
    },
    {
      "number": 4,
      "type": "choice",
      "stem": "依據國籍法以及入出國及移民法之規定,有關國民定義及權利之相關敘述,下列何者錯誤?",
      "section": "乙、測驗題",
      "options": {
        "A": "我國法制中所稱外國人是指不具有我國國籍者,尚不包含無國籍人士",
        "B": "所謂國民是指具有中華民國國籍者,無論其於臺灣地區是否設有戶籍",
        "C": "出生於中華民國領域內,父母均無可考或均無國籍者,依法取得我國國籍",
        "D": "居住臺灣地區設有戶籍之國民入出國,不須特別依法申請許可"
      },
      "answer": "A"
    },
    {
      "number": 5,
      "type": "choice",
      "stem": "依司法院釋字第708號解釋之見解,關於受驅逐出國外國人之收容,下列敘述何者正確?",
      "section": "乙、測驗題",
      "options": {
        "A": "暫時收容是嚴重干預人民身體自由之強制處分,依憲法第8條規定,須事先有法院裁定始可為之",
        "B": "收容人於暫時收容期間內對於該收容處分表示不服,內政部移民署應即於 24 小時內將其移送 法院裁定是否予以收容",
        "C": "外國人並無自由進入我國之權利,違法滯留之外國人已構成犯罪行為,暫時收容程序自須等同 刑事被告羈押程序",
        "D": "考量人身自由之重要,暫時收容之期間以15日為上限,並且不得再行延長,內政部移民署須於 15日內完成遣返作業"
      },
      "answer": "B"
    },
    {
      "number": 6,
      "type": "choice",
      "stem": "依臺灣地區與大陸地區人民關係條例規定,下列何者進入大陸地區應經申請,並經內政部會同國 家安全局、法務部及大陸委員會組成之審查會審查許可?",
      "section": "乙、測驗題",
      "options": {
        "A": "國立大學校長",
        "B": "地方議會議員",
        "C": "直轄市長",
        "D": "執政黨黨主席"
      },
      "answer": "C"
    },
    {
      "number": 7,
      "type": "choice",
      "stem": "有關人口販運防制法所稱之人口販運,下列敘述何者正確?",
      "section": "乙、測驗題",
      "options": {
        "A": "收受外國人相當價金,單純協助其非法偷渡入境並交付偽造身分證明者,亦屬人口販運行為",
        "B": "意圖使未滿 18 歲之人從事性交易而運送出境並為媒介,縱事後取得當事人之同意,亦屬人口 販運行為",
        "C": "意圖摘取他人器官而以強暴脅迫方式質押或運送我國人民者,由於涉及人體器官交易,不在人 口販運概念內",
        "D": "意圖進行勞動剝削,而扣留外籍人士重要文件並容留者,由於非直接限制其行動自由,故非屬 人口販運行為"
      },
      "answer": "B"
    },
    {
      "number": 8,
      "type": "choice",
      "stem": "依據海岸巡防法規定,關於海岸巡防機關行使職權,下列敘述何者錯誤?",
      "section": "乙、測驗題",
      "options": {
        "A": "海洋環境之保護及保育,亦屬海巡機關法定職掌事項",
        "B": "海巡機關人員對航行海域內之船舶,如認有損害我國海域利益之虞者,得登臨檢查",
        "C": "海巡機關人員執行職務時,應穿著制服或出示證明文件,並依法不得使用武器",
        "D": "海巡機關人員執行犯罪調查職務時,視同司法警察官或司法警察"
      },
      "answer": "C"
    },
    {
      "number": 9,
      "type": "choice",
      "stem": "我國防制人口販運工作重點可區分為4P,下列何者不在4P 之中?",
      "section": "乙、測驗題",
      "options": {
        "A": "預防(Prevention)",
        "B": "保護(Protection)",
        "C": "起訴(Prosecution)",
        "D": "懲罰(Punishment)"
      },
      "answer": "D"
    },
    {
      "number": 10,
      "type": "choice",
      "stem": "依據海關緝私條例規定,有關海關緝私作業,下列敘述何者正確?",
      "section": "乙、測驗題",
      "options": {
        "A": "海關有正當理由認有身帶物件足以構成違反本條例情事者,得令其交驗該項物件,但不得搜索 身體",
        "B": "海關執行緝私發現有犯罪嫌疑者,為求偵查時效,應自行偵辦案件而無須移送其他主管機關處理",
        "C": "海關因緝私必要,得命船舶停駛、回航至指定地點,對抗不遵照者得以武器射擊",
        "D": "軍警機關在非通商口岸發覺違反本條例之情事時不得逕行查緝,應盡速通報海關到場處理"
      },
      "answer": "C"
    },
    {
      "number": 11,
      "type": "choice",
      "stem": "依據人口販運防制法之規定,對人口販運被害人進行安置保護及送返原籍國之費用,應由下列何 者負擔支付?",
      "section": "乙、測驗題",
      "options": {
        "A": "加害人",
        "B": "被害人之原籍國",
        "C": "我國政府",
        "D": "財團法人犯罪被害人保護協會"
      },
      "answer": "A"
    },
    {
      "number": 12,
      "type": "choice",
      "stem": "雙重犯罪原則為引渡之重要基本原則,其概念內涵為下列何者?",
      "section": "乙、測驗題",
      "options": {
        "A": "引渡人所涉嫌之罪行,於請求引渡國與被請求引渡國皆屬犯罪行為",
        "B": "引渡人於請求引渡國犯罪,且於被請求引渡國亦留有其他犯罪前科",
        "C": "引渡人於請求引渡國犯罪,並且非屬初犯,於該國已有多次犯罪前科",
        "D": "引渡人所涉嫌之罪行,其犯罪行為地橫跨請求引渡國與被請求引渡國"
      },
      "answer": "A"
    },
    {
      "number": 13,
      "type": "choice",
      "stem": "有關海峽兩岸共同打擊犯罪及司法互助協議,下列敘述何者錯誤?",
      "section": "乙、測驗題",
      "options": {
        "A": "該份協議是由我方財團法人海峽交流基金會,與中方海峽兩岸關係協會經平等協商後簽訂",
        "B": "雙方同意交換涉及犯罪有關情資,協助緝捕刑事嫌疑犯,必要時合作協辦與偵查",
        "C": "雙方基於互惠原則,在不違反公序良俗之情況下,相互認可及執行民事確定裁判",
        "D": "雙方同意以海運直航但不包含空運直航方式,遣返刑事犯,並於交接時移送有關卷證"
      },
      "answer": "D"
    },
    {
      "number": 14,
      "type": "choice",
      "stem": "攤販甲於警察A依法執行取締攤販職務時,不服警察取締,竟揮拳攻擊A,導致A受輕傷,A對 甲提出告訴。試問本案中甲之行為應如何論罪?",
      "section": "乙、測驗題",
      "options": {
        "A": "僅成立刑法第135條第1項的妨害公務罪",
        "B": "同時成立刑法第135條第1項的妨害公務罪與刑法第277條第1項的傷害罪,為法條競合,妨 害公務罪被吸收,僅論以傷害罪",
        "C": "同時成立刑法第135條第1項的妨害公務罪與刑法第277條第1項的傷害罪,為想像競合犯從 一重論以傷害罪",
        "D": "同時成立刑法第135條第1項的妨害公務罪與刑法第277條第1項的傷害罪,數罪併罰"
      },
      "answer": "C"
    },
    {
      "number": 15,
      "type": "choice",
      "stem": "關於刑法第10條的諸多立法解釋中,下列敘述何者錯誤?",
      "section": "乙、測驗題",
      "options": {
        "A": "毀敗或嚴重減損他人之味能或嗅能,屬「重傷」",
        "B": "以強暴、脅迫或其他違反人道之方法,對他人施以凌辱虐待,屬「凌虐」",
        "C": "非基於正當目的所為,以器物進入他人口腔之行為,屬「性交」",
        "D": "公務員職務上製作之文書,屬「公文書」"
      },
      "answer": "C"
    },
    {
      "number": 16,
      "type": "choice",
      "stem": "甲企圖對現供A使用之住宅縱火,計畫以汽油作為引火媒介,遂帶著一桶汽油至A宅開始潑灑, 此時碰巧有警車巡邏經過,甲隨即遭警察逮捕。依據實務見解,甲之行為成立何罪?",
      "section": "乙、測驗題",
      "options": {
        "A": "無罪",
        "B": "放火未遂罪",
        "C": "預備放火罪",
        "D": "陰謀放火罪"
      },
      "answer": "C"
    },
    {
      "number": 17,
      "type": "choice",
      "stem": "現行刑法的共犯從屬性係採所謂的「限制從屬性」,此係指共犯之成立必須從屬於一個正犯的:",
      "section": "乙、測驗題",
      "options": {
        "A": "構成要件行為",
        "B": "構成要件該當且具違法性之行為",
        "C": "構成要件該當、違法且具有責性之行為",
        "D": "構成要件該當、違法且具有責性及其他可罰性要件之行為"
      },
      "answer": "B"
    },
    {
      "number": 18,
      "type": "choice",
      "stem": "甲因金錢糾紛而對 A 起殺意,甲遂持刀砍 A 數刀,A 流血不止倒地,此時甲看到 A 全身是血、 突然心生悔悟,覺得自己太過衝動,為避免鑄成大錯,甲趕緊將A送醫急救。之後,A於醫院歷 經緊急手術,但不幸地A仍於3天後死亡。試問甲之行為應如何論處?",
      "section": "乙、測驗題",
      "options": {
        "A": "甲成立殺人未遂罪",
        "B": "甲成立殺人既遂罪",
        "C": "甲成立殺人既遂罪之中止犯",
        "D": "甲成立殺人既遂罪之準中止犯"
      },
      "answer": "B"
    },
    {
      "number": 19,
      "type": "choice",
      "stem": "若犯罪所得已經移轉於第三人手上,則在下列何種情況,不得針對該第三人實施沒收?",
      "section": "乙、測驗題",
      "options": {
        "A": "該第三人明知他人違法行為而取得",
        "B": "該第三人係無償取得",
        "C": "該第三人係支付相當對價而取得",
        "D": "犯罪行為人為該第三人實行違法行為,該第三人因而取得"
      },
      "answer": "C"
    },
    {
      "number": 20,
      "type": "choice",
      "stem": "犯罪偵查中檢察官訊問證人製作之筆錄,法庭審理作為事實之證明,該筆錄之敘述下列何者 正確?",
      "section": "乙、測驗題",
      "options": {
        "A": "屬物的證據",
        "B": "屬傳聞證據",
        "C": "證人有翻供的情形",
        "D": "應有補強證據"
      },
      "answer": "B"
    },
    {
      "number": 21,
      "type": "choice",
      "stem": "刑事訴訟程序應遵守偵查不公開原則,若有違背本原則之情形應負相關罰責。試問下列敘述何者 為本原則之適用對象?",
      "section": "乙、測驗題",
      "options": {
        "A": "辯護人",
        "B": "被告",
        "C": "媒體記者",
        "D": "被害人"
      },
      "answer": "A"
    },
    {
      "number": 22,
      "type": "choice",
      "stem": "刑事法庭審判程序,包括下列階段:(甲)權利告知、(乙)訊問被告、(丙)證據調查、(丁)言 詞辯論。試問上述各項程序步驟排序,下列說明何者正確?",
      "section": "乙、測驗題",
      "options": {
        "A": "丙→甲→乙→丁",
        "B": "甲→丙→乙→丁",
        "C": "甲→乙→丙→丁",
        "D": "乙→甲→丙→丁"
      },
      "answer": "B"
    },
    {
      "number": 23,
      "type": "choice",
      "stem": "員警偵訊犯罪嫌疑人過程,經依刑事訴訟法第 95 條第 1 項規定為權利告知後,同時附加說明: 「保持緘默的意思,就是實話實說」。犯罪嫌疑人聽聞員警上述說明,隨即接受偵訊、製作筆錄。 依據實務見解,下列敘述何者正確?",
      "section": "乙、測驗題",
      "options": {
        "A": "員警違反即時偵訊規定",
        "B": "員警違反緘默權保障規定",
        "C": "員警違反辯護權保障規定",
        "D": "員警違反辯護人在場規定"
      },
      "answer": "B"
    },
    {
      "number": 24,
      "type": "choice",
      "stem": "偵查人員偵訊犯罪嫌疑人過程,若其有要求選任辯護人之情形。下列敘述何者正確?",
      "section": "乙、測驗題",
      "options": {
        "A": "偵訊人員於等待辯護人到場之時間仍可偵訊",
        "B": "等候辯護人之時間計入移送法院時限",
        "C": "偵訊過程中,辯護人可在場並作筆記",
        "D": "偵訊過程中,辯護人在場不得保持緘默"
      },
      "answer": "C"
    },
    {
      "number": 25,
      "type": "choice",
      "stem": "刑事程序偵查階段中,犯罪嫌疑人於下列何時得行使辯護人在場之權利?",
      "section": "乙、測驗題",
      "options": {
        "A": "搜索扣押過程中",
        "B": "勘驗鑑定過程中",
        "C": "實施詢問過程中",
        "D": "拘提逮捕過程中"
      },
      "answer": "C"
    }
  ],
  "year": 110,
  "category": "移民特考",
  "subject": "[四等] 國境執法概要與刑事法概要(包括刑法概要與刑事訴訟法概要)",
  "level": "四等",
  "original_subject": "國境執法概要與刑事法概要(包括刑法概要與刑事訴訟法概要)",
  "source_pdf": "/home/user/police-exam-archive/移民特考PDF/110年/四等/國境執法概要與刑事法概要(包括刑法概要與刑事訴訟法概要)/試題.pdf",
  "file_type": "試題",
  "total_questions": 27
}