{
  "metadata": {
    "exam_type": "109",
    "exam_name": "一般警察人員考試",
    "level": "三等",
    "subject": "外事警察學",
    "exam_time": "2 小時",
    "code": "50250"
  },
  "notes": [
    "※注意：①禁止使用電子計算器。",
    "②不必抄題，作答時請將試題題號及答案依照順序寫在試卷上，於本試題上作答者，不予計分。",
    "③本科目除專門名詞或數理公式外，應使用本國文字作答。"
  ],
  "sections": [],
  "questions": [
    {
      "number": "一",
      "type": "essay",
      "stem": "外事警察的服務對象以外國籍人士為主。因此,外語程度之要求,亦是\n成為一名優秀外事警察的必備條件之一。請用英文寫出下列在服務外國\n人之相關業務中,常用的詞彙:\n①多重國籍。(2 分)\n②歸化。(2 分)\n③懼外症(又稱仇外心理)。(3 分)\n④歧視。(2 分)\n⑤生物特徵。(2 分)\n⑥新冠病毒。(2 分)\n⑦不受歡迎人物。(2 分)\n⑧大麻。(2 分)\n⑨人口販運。(2 分)\n⑩外交豁免權。(2 分)\n⑪特權。(2 分)\n⑫觀光警察。(2 分)",
      "section": null
    },
    {
      "number": "二",
      "type": "essay",
      "stem": "陳小姐因有親友基於家庭因素,而取得雙重國籍,因而對我國規範國籍\n之相關議題,產生高度興趣。\n試說明下列問題:\n①我國國民提出喪失國籍之申請,內政部在那些情形下,許可其申請?\n(10 分)\n②中華民國國民取得外國國籍者,不得擔任中華民國公職,但那些公職\n經該管主管機關核准者,不在此限?(15 分)",
      "section": null
    },
    {
      "number": "三",
      "type": "essay",
      "stem": "某警察分局據報轄內某豆腐工廠有聘僱非法外籍移工,經調查在廠內的\n三位外籍移工,都屬合法引進。但經相關人員通譯方知,該三人已來此\n工廠二年,其陳述的相關事實如下:雇主扣押護照及證件,且不准對外\n聯絡。出入均有專人監控,無法自由行動。不給休假、不給加班費,每\n月只拿到四千元。因為不諳中文又不懂法令,只好忍氣吞聲,暗自哭泣。\n試說明下列問題:\n①司法警察人員於調查此類案件時,應注意相關人員是否有那些疑似人\n口販運被害人之情形?(15 分)\n②各級主管機關、勞工主管機關對於安置保護之人口販運被害人及疑似\n人口販運被害人,應自行或委託民間團體,提供那些協助?(10 分)",
      "section": null
    },
    {
      "number": "四",
      "type": "essay",
      "stem": "某警察局的員警在執行夜市巡邏勤務時,查獲有一餐廳僱用二名外籍女\n服務生,經查卻發現她們係雇主聘僱的家庭看護,但雇主卻又要求她們\n至夜市餐廳工作,這種雇主違規的行為,相關單位在處理外籍移工案件\n時,乃經常發現的現象。試說明下列問題:\n①依相關法令,說明雇主聘僱外國人不得有那些情事?(15 分)\n②雇主聘僱外國人工作,應檢具有關文件,向中央主管機關申請許可。\n但有那些情形之一,不須申請許可?(10 分)",
      "section": null
    }
  ],
  "year": 109,
  "category": "外事警察學系學",
  "subject": "外事警察學",
  "source_pdf": "考古題庫\\外事警察學系\\109年\\外事警察學系學\\試題.pdf",
  "file_type": "試題"
}
