{
  "metadata": {
    "exam_type": "107",
    "exam_name": "一般警察人員考試",
    "level": "三等"
  },
  "notes": [
    "※注意： ①本試題為單一選擇題，請選出一個正確或最適當的答案，複選作答者，該題不予計分。",
    "②共50題，每題2分，須用2B鉛筆在試卡上依題號清楚劃記，於本試題上作答者，不予計分。",
    "③禁止使用電子計算器。"
  ],
  "sections": [],
  "questions": [
    {
      "number": 1,
      "type": "choice",
      "stem": "申請解除「警示帳戶」,應向何機關申請? (A)金融機構 (B)金融監督管理委員會 (C)原通報單位 (D)法院或檢察署",
      "section": null,
      "answer": "C"
    },
    {
      "number": 2,
      "type": "choice",
      "stem": "關於洗錢防制法所規定之「特定犯罪所得」,下列敍述何者錯誤? (A)包括特定犯罪而取得之財物 (B)特定犯罪所得之認定,乃以其所犯特定犯罪經有罪判決為必要 (C)包括特定犯罪變得之財物 (D)包括特定犯罪而取得之財產上利益及其孳息",
      "section": null,
      "answer": "B"
    },
    {
      "number": 3,
      "type": "choice",
      "stem": "依據民國107年1月3日修正「組織犯罪防制條例」規定,有關「組織犯罪」之敘述,下列何者錯誤? (A)犯罪組織,不以現存者為必要 (B)犯罪組織,指三人以上,所組成具有持續性及牟利性之有結構性組織 (C)組織犯罪之被害人或證人於境外時,得利用聲音、影像傳真之科技設備為訊問、詰問 (D)於偵查或審判中對組織犯罪之被害人或證人為訊問、詰問或對質,得依聲請或依職權在法庭外為之",
      "section": null,
      "answer": "B"
    },
    {
      "number": 4,
      "type": "choice",
      "stem": "刑案現場處理,有關「救護傷患」之敘述,下列何者錯誤? (A)警察人員抵達現場後,應視現場狀況,探查是否有人受傷 (B)受傷者不論其為被害人或加害人,均應迅速予以救護或送醫,並視情形,作必要之保護或戒護 (C)救護傷患時,應儘量避免破壞現場痕跡,如確屬無法避免時,應為必要之記錄 (D)警察人員護送傷患就醫時,宜詢問案件發生之事實真相並記錄,傷患衣物,應速棄置處理",
      "section": null,
      "answer": "D"
    },
    {
      "number": 5,
      "type": "choice",
      "stem": "刑案現場處理,有關「現場保全」之敘述,下列何者錯誤? (A)實施封鎖時,應派員於封鎖線外警戒。非經現場指揮官同意,任何人不得進入,以免破壞現場跡證 (B)經許可進入現場者,應著帽套、手套、鞋套或其他裝備 (C)現場封鎖範圍應視現場環境及事實需要而定,原則以三道封鎖線為準,必要時得實施交通管制 (D)初期封鎖之範圍宜窄,以避免影響交通,待初步勘察後,視實際需要再行界定封鎖範圍",
      "section": null,
      "answer": "D"
    },
    {
      "number": 6,
      "type": "choice",
      "stem": "為免跡證遭受風吹、雨淋、日曬等自然力所破壞,下列何者非屬初抵現場人員應有之作為? (A)設法採取跡證 (B)使用帳蓬、雨棚或其他物品保全跡證 (C)為適當之記錄 (D)移至安全地點",
      "section": null,
      "answer": "A"
    },
    {
      "number": 7,
      "type": "choice",
      "stem": "有關「強制處分與任意處分」之敘述,下列何者錯誤? (A)偵查方式,可分為以強制處分進行偵查與任意偵查二類 (B)強制處分因侵害人民受憲法保障的基本權,須遵守法律保留原則 (C)任意偵查因未行使強制力,雖無法律明文,檢察官或司法警察亦可使用 (D)檢察官起訴後,這個階段的調查證據,仍得為強制偵查",
      "section": null,
      "answer": "D"
    },
    {
      "number": 8,
      "type": "choice",
      "stem": "刑案現場無論是如何混亂,初抵現場員警應記住優先處理原則,依序為何? (A)實施現場勘察、案情研判、提出偵查計畫等;再救護傷患、逮捕嫌犯、初步訪問(留置目擊證人)、 現場保全 (B)救護傷患、逮捕嫌犯、初步訪問(留置目擊證人)、現場保全等;再實施現場勘察、案情研判、 提出偵查計畫 (C)案情研判、提出偵查計畫、實施現場勘察、現場保全等;再初步訪問(留置目擊證人)、救護傷 患、逮捕嫌犯 (D)救護傷患、實施現場勘察、案情研判、提出偵查計畫等;再逮捕嫌犯、初步訪問(留置目擊證人)、 現場保全",
      "section": null,
      "answer": "B"
    },
    {
      "number": 9,
      "type": "choice",
      "stem": "勘察組負責現場勘察、採證與記錄。下列何者非屬「勘察組」之主要任務? (A)運用科學技術與方法勘察現場、蒐集證據,作為犯罪偵查或法庭偵審之證據 (B)研判犯罪嫌疑人進出路線、犯罪時間、方法、手段、工具、犯行、過程等,以明瞭犯罪事實 (C)採集各類跡證,並依其特性分別記錄、陰乾、冷藏、包裝、封緘,審慎正確處理,避免污染 (D)依案情需要,對於現場相關處所進行搜查,尋找可能遺留之各種跡證,發掘可能之線索",
      "section": null,
      "answer": "D"
    },
    {
      "number": 10,
      "type": "choice",
      "stem": "下列何種證據的形成,不符合「路卡交換原理」的敘述? (A)性侵犯身上有被害人毛髮 (B)車禍被害人身上有胎痕 (C)指認人描述嫌犯特徵及過程 (D)犯嫌鞋底表面沾附之灰塵",
      "section": null,
      "answer": "C"
    },
    {
      "number": 11,
      "type": "choice",
      "stem": "有關「詢問」之敘述,下列何者正確? (A)檢警因調查犯罪嫌疑人犯罪情形及蒐集證據之必要,得使用通知書,通知犯罪嫌疑人到場詢問 (B)經合法通知,無正當理由不到場者,得報請法官核發拘票 (C)詢問通知書,由司法警察機關主管長官簽名 (D)司法警察官或司法警察詢問犯罪嫌疑人,完全禁止於夜間行之",
      "section": null,
      "answer": "C"
    },
    {
      "number": 12,
      "type": "choice",
      "stem": "下列有關「證人保護」之敘述,下列何者錯誤? (A)證人有依證人保護法規定施以保護之必要者,應請證人書立切結書 (B)證人保護,僅法官能核發證人保護書,採絕對法官保留原則 (C)證人保護,時間急迫者,得先採取必要之保護措施,並於7日內陳報 (D)證人保護法規定之保護措施,應就個案狀況需要審慎選定之",
      "section": null,
      "answer": "B"
    },
    {
      "number": 13,
      "type": "choice",
      "stem": "依海關執行毒品控制下交付作業要點規定,有關「控制下交付」之敘述,下列何者錯誤? (A)為配合檢察或司法機關依毒品危害防制條例第32條之1規定偵辦跨國性毒品犯罪案件 (B)檢警應依據並檢附檢察官核發之偵查指揮書,通知海關配合辦理有關控制下交付作業 (C)專責單位對檢警完成控制下交付後之偵辦結果應予以追蹤,俾得為必要之處置 (D)各關接獲控制下交付案件,應即辦理密報登錄,並以密件處理",
      "section": null,
      "answer": "B"
    },
    {
      "number": 14,
      "type": "choice",
      "stem": "依各級警察機關處理刑案逐級報告紀律規定,下列有關「重大刑案之通報時間起算點」之敘述,下 列何者錯誤? (A)受理他轄發生案件,應即時通報管轄機關並傳送相關資料,管轄機關應於接獲通報後 2 小時內填 輸發生通報單 (B)破獲他轄未通報之案件,除應依單一窗口規定通報發生地轄區分局外,由破獲單位代填輸發破通 報單 (C)刑案紀錄表應於案件發生及破獲後24小時內填輸,逾時依認定基準懲處 (D)經媒體報導社會矚目案件者,於發現犯罪或接獲報案後,應於案件發生30分鐘內,完成初報",
      "section": null,
      "answer": "C"
    },
    {
      "number": 15,
      "type": "choice",
      "stem": "下列何種採取潛伏指紋之增顯技術處理法,通常用於非吸水性材質、光滑表面之物件,例如五金、塑膠等? (A)氰丙烯酸酯法 (B)寧海德林法 (C)硝酸銀法 (D)碘燻法",
      "section": null,
      "answer": "A"
    },
    {
      "number": 16,
      "type": "choice",
      "stem": "下列何種非屬常見的「血跡呈色試劑」處理法? (A)發光胺法 (B)酚酞法 (C)孔雀綠法 (D)蘇丹黑法",
      "section": null,
      "answer": "D"
    },
    {
      "number": 17,
      "type": "choice",
      "stem": "下列何者為新北市政府警察局首創鑑識與犯罪情資整合「大數據」連結分析,作為追蹤查緝犯罪之 偵查利器? (A)車牌辨識追蹤系統 (B)DNA生物辨識查緝系統 (C)CSI智慧查緝系統 (D)RNA自動辨識查緝系統",
      "section": null,
      "answer": "C"
    },
    {
      "number": 18,
      "type": "choice",
      "stem": "偵辦電腦犯罪案件,涉及系統入侵、網路洗錢等重大案件者,得會同內政部警政署刑事警察局那一 個偵查大隊協助偵辦? (A)偵查第三大隊 (B)偵查第五大隊 (C)偵查第七大隊 (D)偵查第九大隊",
      "section": null,
      "answer": "D"
    },
    {
      "number": 19,
      "type": "choice",
      "stem": "下列何者非屬刑責區員警依轄區治安狀況,自行建立之資料表? (A)不良幫派組合份子列管名冊 (B)治安顧慮人口名冊 (C)觸法及虞犯少年名冊 (D)通緝查詢逃犯名冊",
      "section": null,
      "answer": "D"
    },
    {
      "number": 20,
      "type": "choice",
      "stem": "中華電信的IP分為行動上網(中華電信emome)及居家寬頻光纖網路(中華電信HiNet)兩種形式, 而HiNet所屬的 IP 網段是可以在投單系統中查調,但中華行動上網 emome所屬的 IP 網段必須發文 向中華電信查詢,下列何者非屬該IP之查詢依據? (A)刑事訴訟法第230條 (B)刑事訴訟法第231條第2項 (C)電信事業處理有關機關(構)查詢電信使用者資料實施辦法第3條 (D)通訊保障及監察法第11條之1",
      "section": null,
      "answer": "D"
    },
    {
      "number": 21,
      "type": "choice",
      "stem": "有關「執行電腦搜索應注意事項」之敘述,下列何者錯誤? (A)電腦檔案之證據應當場列印,並請受搜索人簽名按指印 (B)搜索對象如為學校,應會同該校系主任或相當職務人員執行之 (C)勿安裝或拷貝任何程式、檔案至受搜索人的電腦中 (D)應讓受搜索人與電腦保持適當距離,避免受搜索人接觸電腦刪除檔案、證據",
      "section": null,
      "answer": "B"
    },
    {
      "number": 22,
      "type": "choice",
      "stem": "依106年11月14日修正之「採驗尿液實施辦法」規定,有關「尿液採驗」之敘述,下列何者正確? (A)尿液檢體應分別裝入二瓶尿液容器,每瓶尿液量須達60毫升,並由應受尿液採驗人按捺右大拇指 指紋封緘 (B)應受尿液採驗人右大拇指無法按捺指紋時,應依左手大拇指、左食指等之順序捺印指紋,並由採 尿人員附註該指名稱 (C)尿液檢體溫度未達攝氏32度或超過攝氏38度或內有浮懸物存在或顏色顯有異常者,應重新採尿 (D)尿液初驗應由管轄檢察官或法院決定之,複驗應送至衛生福利部認可之濫用藥物尿液檢驗機關(構)",
      "section": null,
      "answer": "C"
    },
    {
      "number": 23,
      "type": "choice",
      "stem": "查獲疑似毒品製造工廠時,現場相關物質宜全部採集、秤重,並酌採多少公克(顆)送驗,不滿者, 得全部送驗? (A)5 (B)10 (C)20 (D)30",
      "section": null,
      "answer": "B"
    },
    {
      "number": 24,
      "type": "choice",
      "stem": "有關「射擊殘跡證物之處理原則」之敘述,下列何者錯誤? (A)採取射擊殘跡,應以黏有雙面碳膠之鋁(銅)座分別黏取不同部位,並分別標示其採證位置 (B)採取衣物之射擊殘跡,宜於案發後12小時內儘速採集未經清洗、血跡污染之最外層衣物表面殘跡 (C)採取手部射擊殘跡,宜於案發後12小時內儘速採集未經清洗、擦拭、救護之手部殘跡 (D)同案查獲槍彈證物,宜同時採取其彈殼內射擊殘跡備驗",
      "section": null,
      "answer": "C"
    },
    {
      "number": 25,
      "type": "choice",
      "stem": "關於偵辦性侵害案,對犯罪嫌疑人施以身體檢查,下列敘述何者錯誤? (A)司法警察對於拘提到案之犯罪嫌疑人,有相當理由認為唾液得作為犯罪之證據時,得採取其唾液 (B)司法警察因調查犯罪情形之必要,對於傳喚到案之犯罪嫌疑人,得違反其意思,予以照相 (C)鑑定人因鑑定之必要,得經檢察官之許可,採取犯罪嫌疑人之血液 (D)檢察事務官因蒐集證據之必要,對拘提到案之犯罪嫌疑人,得違反其意思,採取其指紋",
      "section": null,
      "answer": "B"
    },
    {
      "number": 26,
      "type": "choice",
      "stem": "通訊保障及監察法修正施行後,對警察機關查察賄選,下列敘述何者錯誤? (A)最輕本刑為3年以上有期徒刑之賄選罪類型,均得聲請通訊監察書 (B)查察賄選通訊監察書之聲請,應以單一監察對象為限,即以人為單位,一人一監聽票 (C)查察賄選同一偵查案號下,若數人犯罪即應聲請數張監聽票,一人犯數罪者,則仍為一張監聽票 (D)對於賄選案類,如有調取通信紀錄之必要時,應依規定向檢察官聲請調取票",
      "section": null,
      "answer": "D"
    },
    {
      "number": 27,
      "type": "choice",
      "stem": "分局受理或接獲分駐所、派出所或其他單位轉報之特殊、重大刑案,除迅速通知偵查隊偵辦外,均 應立即報告主管,並轉報那個單位列管? (A)內政部警政署刑事警察局偵防犯罪指揮中心 (B)地方檢察署 (C)警察局勤務指揮中心 (D)內政部警政署勤務指揮中心",
      "section": null,
      "answer": "C"
    },
    {
      "number": 28,
      "type": "choice",
      "stem": "特殊、重大或普通刑案發生與破獲時機,如係重大變化或重要階段告一段落時,必須如何報告? (A)初報 (B)續報 (C)複報 (D)結報",
      "section": null,
      "answer": "B"
    },
    {
      "number": 29,
      "type": "choice",
      "stem": "司法警察機關對於其移送案件之被告受羈押者,認為有帶同被告外出繼續追查贓證時,得報請檢察 官核發偵查指揮書,交警察機關帶同被告繼續查證,惟應於當日何時前解交檢察官? (A)11時 (B)18時 (C)23時 (D)24時",
      "section": null,
      "answer": "C"
    },
    {
      "number": 30,
      "type": "choice",
      "stem": "刑案分為重大刑案、特殊刑案及普通刑案,下列何者不是特殊刑案? (A)深切影響社會治安、震撼社會人心之案件 (B)犯罪手段殘酷、情節離奇案件 (C)竊取槍械、軍火或國防上之重要設施、器材 (D)新發現之嚴重犯罪手法,必須迅速偵破,予以遏止之案件",
      "section": null,
      "answer": "C"
    },
    {
      "number": 31,
      "type": "choice",
      "stem": "情報諮詢,下列敘述何者錯誤? (A)遴選諮詢對象,以社會各階層、各行業熱心公益及樂於協助維護社會治安人士為原則 (B)凡經遴選諮詢工作請求合作之對象,應依規定列冊備查,發給證件,但不得給予任何名義 (C)交付諮詢對象任務,應謹慎保密,講求方法,並應以蒐集危害國家安全、社會犯罪偵防有關情報 為要點,不得使其直接參與辦案行動 (D)諮詢人員提供情報線索,應詳核其動機、目的及可靠性,如因而及時防止治安事故,或偵破重大 案件,應立即簽報,予以適當獎勵及支應必要費用",
      "section": null,
      "answer": "B"
    },
    {
      "number": 32,
      "type": "choice",
      "stem": "下列何者非「偵查開始原因」? (A)告訴 (B)告發 (C)自訴 (D)自首",
      "section": null,
      "answer": "C"
    },
    {
      "number": 33,
      "type": "choice",
      "stem": "關於勘察採證,下列敘述何者錯誤? (A)重大刑案由管轄警察局偵查隊長或其他代理人擔任現場指揮官 (B)實施現場勘察,於必要時得依相關規定請求支援 (C)對於任何跡證或線索,均應縝密而為 (D)必要時,須重返現場數度勘察或重建",
      "section": null,
      "answer": "A"
    },
    {
      "number": 34,
      "type": "choice",
      "stem": "重大刑案發生,除立即偵破外,均應訂定偵查計畫,下列何者非偵查計畫內容? (A)犯罪人生活情形 (B)發現經過或受理報案經過 (C)偵查實施及分工 (D)協調聯繫",
      "section": null,
      "answer": "A"
    },
    {
      "number": 35,
      "type": "choice",
      "stem": "偵查人員,如必須實施被害人、檢舉人或目擊證人指認犯罪嫌疑人,下列要領何者錯誤? (A)指認前應由指認人先陳述犯罪嫌疑人之特徵 (B)被指認之數人在外形上不得有重大差異 (C)實施照片指認,得以單一相片提供指認,但避免提供老舊照片指認 (D)應為非一對一之成列指認(選擇式指認)",
      "section": null,
      "answer": "C"
    },
    {
      "number": 36,
      "type": "choice",
      "stem": "為調查犯罪情形,通知證人之通知書應於應到時間幾小時前送達? (A)12小時 (B)24小時 (C)36小時 (D)48小時",
      "section": null,
      "answer": "B"
    },
    {
      "number": 37,
      "type": "choice",
      "stem": "刑案證物,子彈、彈頭證物之處理原則,下列敘述何者錯誤? (A)以金屬器具直接夾取彈頭,宜以證物袋分別包裝,避免彼此碰撞 (B)現場子彈、彈頭採取前宜先記錄其原始狀態,並以適當方法採取 (C)現場彈頭應視個案情況留意其上可能之微物跡證 (D)若有供比對之同廠牌子彈,應準備3顆以上送驗",
      "section": null,
      "answer": "A"
    },
    {
      "number": 38,
      "type": "choice",
      "stem": "筆錄不得竄改、挖補或留空行,下列敘述何者錯誤? (A)如有增刪更改,應由製作人或受詢問人在其上蓋章或按指印 (B)其刪除處應留存原字跡,並應於眉欄處記明更改字數 (C)詢問犯罪嫌疑人筆錄之製作,應採一人詢問,另一人記錄之方式製作 (D)檢察官執行詢問、搜索、勘驗時,如無書記官在場,得指定在場執行公務之警察人員製作筆錄",
      "section": null,
      "answer": "A"
    },
    {
      "number": 39,
      "type": "choice",
      "stem": "有關「告訴乃論之罪」之敘述,下列何者錯誤? (A)告訴乃論之罪,如果要撤回告訴,應於第二審法院言詞辯論終結前撤回 (B)以告訴是否為訴訟要件,得將犯罪分為告訴乃論之罪與非告訴乃論之罪 (C)告訴乃論之罪,不僅是偵查發動的原因,亦是訴訟要件,如有欠缺即無法追訴、處罰 (D)告訴乃論之罪,如無得為告訴之人,檢察官得依職權指定代行告訴人",
      "section": null,
      "answer": "A"
    },
    {
      "number": 40,
      "type": "choice",
      "stem": "有關拘提,下列敘述何者正確? (A)拘提有公務員或軍人之犯罪嫌疑人,不必知照該管機關長官協助執行 (B)拘票有二聯,執行拘提時,應一聯交被拘提人或其家屬,另一聯交當地里長 (C)拘票得聲請數通,分交數人分別執行,並得於轄區外執行,不必會同當地警察單位 (D)偵查犯罪,如有在執行或在押中脫逃者,情況急迫,不及報告檢察官,得逕行拘提之",
      "section": null,
      "answer": "D"
    },
    {
      "number": 41,
      "type": "choice",
      "stem": "司法警察人員執行搜索,下列敘述何者錯誤? (A)有人居住或看守之住宅,或其他處所,不得於夜間入內搜索 (B)日間已開始搜索者,得繼續至夜間 (C)飲食店或其他於夜間公眾可出入之處所,仍在公開時間內者,夜間亦不得入內搜索 (D)常用為賭博、妨害性自主或妨害風化之行為者,得入內搜索",
      "section": null,
      "answer": "C"
    },
    {
      "number": 42,
      "type": "choice",
      "stem": "搜索發現可為證據或得沒收之物,得扣押之,發現本案應扣押之物為搜索票所未記載者,亦得扣押 之,惟應於執行扣押後多少時間內報告該管檢察官及法院? (A)12小時內 (B)1日內 (C)2日內 (D)3日內",
      "section": null,
      "answer": "D"
    },
    {
      "number": 43,
      "type": "choice",
      "stem": "關於警察機關偵查刑案,下列敘述何者正確? (A)檢察官命令移送者,得將全案移送管轄法院或檢察署 (B)告訴乃論案件,經撤回告訴者,而告訴人已向檢察官告訴者,不必再函送管轄法院或檢察署 (C)證據證明力薄弱或行為事實是否構成犯罪顯有疑義者,得函送管轄法院或檢察署 (D)全案雖未調查完畢,但經依法提起自訴或向檢察官告訴者,得函送管轄法院或檢察署",
      "section": null,
      "answer": "C"
    },
    {
      "number": 44,
      "type": "choice",
      "stem": "關於組織犯罪案件之處理,下列敘述何者錯誤? (A)犯罪證物之蒐集,應注意公司企劃書、帳冊等物件,必要時並得協請會計專業人員支援解讀 (B)檢舉人身分資料,應予封存、並附入移送法院審理之文書 (C)證人或與其密切利害關係之人、檢舉人及被害人,應依證人保護法克盡保密與保護的責任 (D)偵辦涉及幫派組合成員或有組織犯罪模式之刑案時,應注意蒐證是否符合組織犯罪防制條例之要件",
      "section": null,
      "answer": "B"
    },
    {
      "number": 45,
      "type": "choice",
      "stem": "刑案紀錄表應於受理刑案發生或破獲移送之時起,幾小時內填輸? (A)12小時 (B)24小時 (C)36小時 (D)48小時",
      "section": null,
      "answer": "D"
    },
    {
      "number": 46,
      "type": "choice",
      "stem": "生物跡證的保存原則,下列敘述何者錯誤? (A)現場生物跡證,直接置於紙袋保存 (B)血液、尿液等液態證物,應冷藏保存 (C)肌肉、骨骼、人體組織等,宜冷凍保存 (D)上述跡證立即送鑑者,可冷藏暫存",
      "section": null,
      "answer": "A"
    },
    {
      "number": 47,
      "type": "choice",
      "stem": "無被害者犯罪(Crime without victim)此類犯罪型態雖無明顯法益之侵害,但卻存有極大之非法交易 市場,下列何者非屬無被害者犯罪? (A)墮胎 (B)賭博 (C)賄選 (D)藥物濫用",
      "section": null,
      "answer": "C"
    },
    {
      "number": 48,
      "type": "choice",
      "stem": "擄人勒贖案件中,犯罪的被害者對於加害者產生情感、同情加害者、認同加害者的某些觀點和想法, 甚至反過來幫助加害者的一種情結,稱為: (A)倫敦症候群 (B)斯德哥爾摩症候群 (C)煮蛙效應 (D)蝴蝶效應",
      "section": null,
      "answer": "B"
    },
    {
      "number": 49,
      "type": "choice",
      "stem": "關於偵查守則,下列敘述何者錯誤? (A)偵查刑案以現場為基礎,運用科學器材與方法 (B)自由、法治、科學、人權為偵查犯罪應遵守之原則 (C)偵查刑案,本於虛心求證之科學精神,切忌先入為主之主觀判斷 (D)執行偵查任務人員,如與犯罪嫌疑人、被害人或關係人具有親屬關係,應予迴避",
      "section": null,
      "answer": "B"
    },
    {
      "number": 50,
      "type": "choice",
      "stem": "涉外案件之處理,下列敘述何者錯誤? (A)警察偵查犯罪不得任意進入使領館人員之住宅。如認有必要進入者,應事先徵得當事人同意始得 進入。進入後未經館長同意者,不得翻閱、借用或影印文件 (B)發現享有與外交人員相當待遇之外國人員之家屬涉有犯罪嫌疑者,應即陳報內政部警政署轉外交 部核辦;同時逕行訊問、搜索等強制作為 (C)依法逮捕之一般外國人,於逮捕拘提、收容或羈押後,如當事人明示反對通知其本國駐華使領館 或駐華機構者,可不必通知 (D)外國使領館僱用我國籍之職員,如有犯罪嫌疑者,依一般法定程序處理",
      "section": null,
      "answer": "B"
    }
  ],
  "year": 107,
  "category": "鑑識科學",
  "subject": "犯罪偵查",
  "source_pdf": "考古題庫\\鑑識科學\\107年\\犯罪偵查\\試題.pdf",
  "file_type": "試題"
}