{
  "metadata": {
    "exam_type": "110",
    "exam_name": "警察人員考試",
    "level": "三等",
    "subject": "交通統計與分析",
    "exam_time": "2 小時",
    "code": "50770"
  },
  "notes": [
    "※注意：①可以使用電子計算器。",
    "②不必抄題，作答時請將試題題號及答案依照順序寫在試卷上，於本試題上作答者，不予計分。",
    "③本科目除專門名詞或數理公式外，應使用本國文字作答。",
    "註：",
    "χ²(0.05;5) = 1.145; χ²(0.05;4) = 0.711; χ²(0.05;3) = 0.352",
    "χ²(0.95;5) = 11.07; χ²(0.95;4) = 9.49; χ²(0.95;3) = 7.81",
    "t(0.95;2) = 2.920; t(0.95;120) = 1.658; t(0.95;∞) = 1.645",
    "t(0.975;2) = 4.303; t(0.975;120) = 1.980; t(0.975;∞) = 1.960",
    "常態分配 p.d.f: f(x) = (1/√(2πσ²)) e^(-(x-μ)²/(2σ²))"
  ],
  "sections": [],
  "questions": [
    {
      "number": "一",
      "type": "essay",
      "stem": "您是一位交通工程師,負責檢討訂定某市區幹道路段最高速限,該路段\n現點速率(Spot Speed)調查結果如下表所示。\n速率群組(公里/小時)\n觀測次數\n下限 組中點 上限",
      "section": null
    },
    {
      "number": "二",
      "type": "essay",
      "stem": "①試詳述多元迴歸(Multiple Regression)之假設。(10 分)\n②您是一位運輸規劃師,欲建立旅次吸引(Trip Attraction)之多元迴歸分析模式,蒐集之基年相關變數資料如下:\nA_I = 尖峰小時旅次吸引數\nX₁ = 總就業人口數\nX₂ = 製造業就業人口數\nX₃ = 零售與服務業就業人口數\nX₄ = 其他行業就業人口數\n上述資料經初步分析,得到下列相關矩陣(Correlation Matrix):\n       A_I   X₁    X₂    X₃    X₄\nA_I    1.00  0.996 0.958 0.552 0.124\nX₁          1.00  0.978 0.486 0.110\nX₂                1.00  0.297 0.068\nX₃                      1.00  0.073\nX₄                            1.00\n經建立四個可能的迴歸分析方程式:\nA_I = 61.4 + 0.93X₁, S = 288.4, R² = 0.992, t = 42\nA_I = 507.7 + 0.98X₂, S = 935.9, R² = 0.921, t = 14\nA_I = -69.9 + 1.26X₂ - 0.37X₃ + 0.02X₄, S = 142.6, R² = 0.998, t = 37, 1.1, 0.06\nA_I = 25.8 + 0.89X₂ + 1.29X₃, S = 199.4, R² = 0.996, t = 51, 17\n試分析上述四個迴歸式之適用性。您將選擇那一個方程式?說明您選擇的理由。(15 分)",
      "stem_latex": "①試詳述多元迴歸(Multiple Regression)之假設。(10 分)\n②您是一位運輸規劃師,欲建立旅次吸引(Trip Attraction)之多元迴歸分析模式,蒐集之基年相關變數資料如下:\n$A_I$ = 尖峰小時旅次吸引數\n$X_1$ = 總就業人口數\n$X_2$ = 製造業就業人口數\n$X_3$ = 零售與服務業就業人口數\n$X_4$ = 其他行業就業人口數\n上述資料經初步分析,得到下列相關矩陣(Correlation Matrix):\n       $A_I$  $X_1$  $X_2$  $X_3$  $X_4$\n$A_I$  1.00   0.996  0.958  0.552  0.124\n$X_1$         1.00   0.978  0.486  0.110\n$X_2$                1.00   0.297  0.068\n$X_3$                       1.00   0.073\n$X_4$                              1.00\n經建立四個可能的迴歸分析方程式:\n$A_I = 61.4 + 0.93X_1$, $S = 288.4$, $R^2 = 0.992$, $t = 42$\n$A_I = 507.7 + 0.98X_2$, $S = 935.9$, $R^2 = 0.921$, $t = 14$\n$A_I = -69.9 + 1.26X_2 - 0.37X_3 + 0.02X_4$, $S = 142.6$, $R^2 = 0.998$, $t = 37, 1.1, 0.06$\n$A_I = 25.8 + 0.89X_2 + 1.29X_3$, $S = 199.4$, $R^2 = 0.996$, $t = 51, 17$\n試分析上述四個迴歸式之適用性。您將選擇那一個方程式?說明您選擇的理由。(15 分)",
      "section": null
    },
    {
      "number": "三",
      "type": "essay",
      "stem": "某市因交岔路口事故日增,決定針對非號誌化路口增設「停」標誌,並\n進行交通大執法,下表為標誌設置前後車輛行經路口遵循規則與否的調\n查結果。試以列聯表(Contingency Table)分析檢定設置標誌並大執法後\n是否有顯著效果(顯著水準α = 0.05)?(25 分)\n設置前 設置後 總計\n停車再開 25 52 77\n減速慢行 15 12 27\n未停車再開 10 7 17\n總計 50 71 121",
      "stem_latex": "某市因交岔路口事故日增,決定針對非號誌化路口增設「停」標誌,並進行交通大執法,下表為標誌設置前後車輛行經路口遵循規則與否的調查結果。試以列聯表(Contingency Table)分析檢定($\\chi^2$ 檢定)設置標誌並大執法後是否有顯著效果(顯著水準 $\\alpha = 0.05$)?(25 分)\n設置前 設置後 總計\n停車再開 25 52 77\n減速慢行 15 12 27\n未停車再開 10 7 17\n總計 50 71 121",
      "section": null
    },
    {
      "number": "四",
      "type": "essay",
      "stem": "假設一易肇事交岔路口發生事故的件數可以用 Poisson 過程表示,其參\n數為平均每週 2 件。試問:\n①連續二事故發生時間間隔 3 天以上的機率?(10 分)\n②由一事故到下二事故間隔 7 天以上的機率?(15 分)",
      "stem_latex": "假設一易肇事交岔路口發生事故的件數可以用 Poisson 過程表示,其參數為平均每週 $\\lambda = 2$ 件。試問:\n①連續二事故發生時間間隔 3 天以上的機率?(10 分)\n②由一事故到下二事故間隔 7 天以上的機率?(15 分)",
      "section": null
    }
  ],
  "year": 110,
  "category": "交通學系交通組",
  "subject": "交通統計與分析",
  "source_pdf": "考古題庫\\交通學系交通組\\110年\\交通統計與分析\\試題.pdf",
  "file_type": "試題"
}
