{
  "metadata": {
    "exam_type": "110",
    "exam_name": "警察人員考試",
    "level": "三等",
    "subject": "水上警察學",
    "exam_time": "2 小時",
    "code": "51270"
  },
  "notes": [
    "※注意：①禁止使用電子計算器。",
    "②不必抄題，作答時請將試題題號及答案依照順序寫在試卷上，於本試題上作答者，不予計分。",
    "③本科目除專門名詞或數理公式外，應使用本國文字作答。"
  ],
  "sections": [],
  "questions": [
    {
      "number": "一",
      "type": "essay",
      "stem": "近期發生一名中國大陸籍男子駕駛橡皮艇由大陸偷渡來臺遭逮捕,海洋\n委員會海巡署為防制此類由海上以不法手段進入臺灣案件,運用所謂三\n道監偵幕,以防阻非法入境情事,請問海洋委員會海巡署如何運用三道\n監偵幕,防阻由海上非法入境事件?(25 分)",
      "section": null
    },
    {
      "number": "二",
      "type": "essay",
      "stem": "我國推動海洋保育有成,沿海漁業資源豐富,導致他國漁船頻頻至我國\n管轄水域作業,海洋委員會海巡署派遣艦艇予以登檢取締,惟此類漁船\n經常拒絕停船受檢,並加速逃逸,海巡人員遇此狀況,均立即以優勢警\n力追緝、強靠登檢及取締。請問現場登檢指揮官之職責為何?(25 分)",
      "section": null
    },
    {
      "number": "三",
      "type": "essay",
      "stem": "入出漁港及遊艇港之漁船筏或其他運輸工具,海洋委員會海巡署安檢人\n員除依相關法令應執行安全檢查者外,應結合漁船筏評鑑類別、近期情\n資、港區特性調查及可疑徵候研析等,據以認定有無違法之虞。請問漁\n船筏評鑑之分類為何?(25 分)",
      "section": null
    },
    {
      "number": "四",
      "type": "essay",
      "stem": "海岸巡防為國家安全的根本,政府為統一海岸巡防事權及有效管理海\n域,並配合行政院組織調整,成立「海洋委員會海巡署」,持續執行海域\n及海岸巡防五大核心任務。請問海洋委員會海巡署之五大核心任務為\n何?(25 分)",
      "section": null
    }
  ],
  "year": 110,
  "category": "水上警察學系學",
  "subject": "水上警察學",
  "source_pdf": "考古題庫\\水上警察學系\\110年\\水上警察學系學\\試題.pdf",
  "file_type": "試題"
}
