{
  "metadata": {
    "exam_type": "113",
    "exam_name": "警察人員考試",
    "level": "三等",
    "subject": "國家安全情報法制",
    "exam_time": "2 小時",
    "code": "50430"
  },
  "notes": [
    "※注意：①禁止使用電子計算器。",
    "②不必抄題，作答時請將試題題號及答案依照順序寫在試卷上，於本試題上作答者，不予計分。",
    "③本科目除專門名詞或數理公式外，應使用本國文字作答。"
  ],
  "sections": [],
  "questions": [
    {
      "number": "一",
      "type": "essay",
      "stem": "依據「國家情報工作法」,情報機關進行國家安全或利益的資訊蒐集、研\n析、處理與運用,請說明涵蓋何種資訊,蒐集方式及應注意事項為何?\n(25 分)",
      "section": null
    },
    {
      "number": "二",
      "type": "essay",
      "stem": "「通訊保障及監察法」旨在保障人民秘密通訊自由及隱私權,不受非法\n侵害,並確保國家安全,維護社會秩序。執行機關在監聽期間內,應遵\n守那些法律規定?法官在何種情況下可撤銷原核發通訊監察書?違反\n規定進行監聽行為所取得之內容或所衍生之證據,依法該如何處理?\n(25 分)",
      "section": null
    },
    {
      "number": "三",
      "type": "essay",
      "stem": "依據「國家機密保護法」,應如何保護國家機密之複製物?(25 分)",
      "section": null
    },
    {
      "number": "四",
      "type": "essay",
      "stem": "依據「臺灣地區與大陸地區人民關係條例」,大陸地區之營利事業或其於\n第三地區投資之營利事業,非經主管機關許可,並在臺灣地區設立分公\n司或辦事處,不得在臺從事業務活動,請申論之。(25 分)",
      "section": null
    }
  ],
  "year": 113,
  "category": "公共安全學系社安組",
  "subject": "國家安全情報法制",
  "source_pdf": "考古題庫\\公共安全學系社安組\\113年\\國家安全情報法制\\試題.pdf",
  "file_type": "試題"
}
