{
  "metadata": {
    "exam_type": "112",
    "level": "三等",
    "subject": "入出國及移民法規(包括入出國及移民法、人口販運防制法、國籍法、就業服務法、臺灣地區與大陸地區人民關係條例、香港澳門關係條例、護照條例、外國護照簽證條例、涉外民事",
    "exam_time": "2 小時",
    "code": "63160",
    "exam_name": "移民行政人員特種考試",
    "year": 112
  },
  "notes": [
    "※注意：禁止使用電子計算器。",
    "不必抄題，作答時請將試題題號及答案依照順序寫在申論試卷上，於本試題上作答者，不予計分。",
    "請以藍、黑色鋼筆或原子筆在申論試卷上作答。",
    "本科目除專門名詞或數理公式外，應使用本國文字作答。",
    "本試題為單一選擇題，請選出一個正確或最適當答案。",
    "共25題，每題2分，須用2B鉛筆在試卡上依題號清楚劃記，於本試題或申論試卷上作答者，不予計分。"
  ],
  "sections": [
    "甲、申論題",
    "乙、測驗題"
  ],
  "questions": [
    {
      "number": "一",
      "type": "essay",
      "stem": "試述我國移民政策之發展趨勢,並說明移民政策規劃與法規之關係。(25分)",
      "section": "甲、申論題"
    },
    {
      "number": "二",
      "type": "essay",
      "stem": "香港人民 E 君,曾於 2001 年時取得我國護照。後因護照失效,轉而回\n到香港居住。今(2023)年,E 君欲申請回臺定居,試問應以何身分來\n臺,並說明護照失效應如何處理?(25 分)",
      "section": "甲、申論題"
    },
    {
      "number": 1,
      "type": "choice",
      "stem": "依據民國 112 年 6 月 14 日修正公布之人口販運防制法,下列何者非屬人口販運防制法定義中的 「不法作為」?",
      "section": "乙、測驗題",
      "options": {
        "A": "強暴、脅迫、恐嚇、拘禁、監控、藥劑、催眠術、詐術、故意隱瞞重要資訊、不當債務約束、 扣留重要文件、利用他人不能、不知或難以求助之處境,或其他相類之方法",
        "B": "從事招募、買賣、質押、運送、交付、收受、藏匿、隱避、媒介、容留國內外人口",
        "C": "使他人從事有對價之性交或猥褻行為",
        "D": "使人為奴隸或類似奴隸、強迫勞動、從事勞動與報酬顯不相當之工作"
      },
      "answer": "A"
    },
    {
      "number": 2,
      "type": "choice",
      "stem": "中華民國國民雖依國籍法第 11 條第 1 項各款經內政部許可,喪失中華民國國籍,惟下列何種情 形仍不喪失國籍:",
      "section": "乙、測驗題",
      "options": {
        "A": "受有期徒刑以上刑之宣告,已執行完畢者",
        "B": "受強制執行,已終結者",
        "C": "受破產之宣告,已復權者",
        "D": "有滯納租稅或受租稅處分罰鍰未繳清者"
      },
      "answer": "D"
    },
    {
      "number": 3,
      "type": "choice",
      "stem": "依據民國112年人口販運防制法修正條文規定,有關人口販運被害人之鑑別程序,何者有誤?",
      "section": "乙、測驗題",
      "options": {
        "A": "鑑別結果,應作成鑑別通知書送達受鑑別人",
        "B": "受鑑別人對於鑑別結果不服者,得於鑑別通知書送達翌日起20日內,以書面敘明理由,經原鑑 別機關(單位)向其上級機關(單位)提出異議",
        "C": "原鑑別機關(單位)認無理由者,應於15日內加具書面理由送上級機關(單位)決定",
        "D": "上級機關(單位)受理異議後,應於10日內為決定,認異議有理由者,應立即更正之;認無理 由者,應予維持"
      },
      "answer": "C"
    },
    {
      "number": 4,
      "type": "choice",
      "stem": "依據民國112年入出國及移民法修正條文之規定,增加律師可執行之業務,不包括那一項業務?",
      "section": "乙、測驗題",
      "options": {
        "A": "受強制驅逐之外國人得委任律師於陳述意見程序或審查會進行時在場",
        "B": "得辦理移民服務",
        "C": "得辦理婚姻媒合服務",
        "D": "經查驗許可入國(境)後進行面談者,申請人得委任律師在場"
      },
      "answer": "C"
    },
    {
      "number": 5,
      "type": "choice",
      "stem": "依據入出國及移民法第 52 條規定,政府對於計畫移居發生戰亂或瘟疫之國家或地區者,得為下 列何種行為?",
      "section": "乙、測驗題",
      "options": {
        "A": "警告並講習",
        "B": "勸阻",
        "C": "處以罰鍰",
        "D": "禁止出國"
      },
      "answer": "B"
    },
    {
      "number": 6,
      "type": "choice",
      "stem": "某甲居住於印度但為無國籍人士,後為我國人之配偶,其欲申請歸化我國國籍,應向何機關為之?",
      "section": "乙、測驗題",
      "options": {
        "A": "內政部",
        "B": "外交部",
        "C": "蒙藏事務主管機關",
        "D": "各縣市政府"
      },
      "answer": "A"
    },
    {
      "number": 7,
      "type": "choice",
      "stem": "有關雇主聘僱就讀於公立大專校院之外國留學生從事工作之規定,下列何者正確?",
      "section": "乙、測驗題",
      "options": {
        "A": "不得聘僱",
        "B": "得聘僱,惟其工作時間除寒暑假外,每星期最長為14小時",
        "C": "得聘僱,惟其工作時間除寒暑假外,每星期最長為20小時",
        "D": "得聘僱,惟其工作時間除寒暑假外,每星期最長為28小時"
      },
      "answer": "C"
    },
    {
      "number": 8,
      "type": "choice",
      "stem": "防制人口販運工作應以保護被害人權益為核心,人口販運被害人依民國112年人口販運防制法修 正條文之規定,可以獲得之協助不含下列何者?",
      "section": "乙、測驗題",
      "options": {
        "A": "人身安全保護",
        "B": "在外居住房屋租金補貼",
        "C": "就業技能及教育訓練",
        "D": "申請歸化國籍"
      },
      "answer": "D"
    },
    {
      "number": 9,
      "type": "choice",
      "stem": "依據護照條例施行細則之規定,護照之頁數由主管機關定之,空白內頁不足時,得加頁使用。但 以幾次為限?",
      "section": "乙、測驗題",
      "options": {
        "A": "1次",
        "B": "2次",
        "C": "3次",
        "D": "4次"
      },
      "answer": "A"
    },
    {
      "number": 10,
      "type": "choice",
      "stem": "依據民國 112 年 6 月 14 日修正公布之人口販運防制法,經鑑別為人口販運被害人者,中央主管 機關應依其申請,核發多久效期的停/居留許可?",
      "section": "乙、測驗題",
      "options": {
        "A": "3個月效期的臨時停留許可",
        "B": "6個月效期的臨時停留許可",
        "C": "6個月效期的居留許可",
        "D": "1年效期的居留許可"
      },
      "answer": "D"
    },
    {
      "number": 11,
      "type": "choice",
      "stem": "兩位臺商因在大陸地區之商業糾紛,在大陸地區人民法院提起訴訟。勝訴的臺商取得大陸民事確 定判決返臺後,得向何機關聲請認可?",
      "section": "乙、測驗題",
      "options": {
        "A": "行政院大陸委員會",
        "B": "海峽兩岸交流基金會",
        "C": "法院",
        "D": "經濟部"
      },
      "answer": "C"
    },
    {
      "number": 12,
      "type": "choice",
      "stem": "臺灣地區人民某甲與澳門居民某乙,因網路購物買賣糾紛衍生之民事事件,其法律適用應為下列 何者?",
      "section": "乙、測驗題",
      "options": {
        "A": "準用香港澳門關係條例",
        "B": "適用涉外民事法律適用法",
        "C": "類推適用涉外民事法律適用法",
        "D": "準用臺灣地區與大陸地區人民關係條例"
      },
      "answer": "C"
    },
    {
      "number": 13,
      "type": "choice",
      "stem": "下列何者非屬依據臺灣地區與大陸地區人民關係條例第9條第9項之規定,得經立法院議決由行 政院公告於一定期間內,對臺灣地區人民進入大陸地區,採行禁止或限制之事由?",
      "section": "乙、測驗題",
      "options": {
        "A": "遇有重大突發事件",
        "B": "影響臺灣地區重大利益",
        "C": "於兩岸互動有重大危害情形",
        "D": "於亞太地區發生重大衝突"
      },
      "answer": "D"
    },
    {
      "number": 14,
      "type": "choice",
      "stem": "依據民國 112 年 6 月 28 日修正公布之入出國及移民法,外國人受強制驅逐出國處分,內政部移 民署得依法暫予收容、向法院聲請裁定續予收容、延長收容。唯若受收容人於延長收容期間屆滿 前,有致無法強制驅逐出國之法定因素,內政部移民署可向法院聲請裁定「再延長收容」,請問「再 延長收容」每次最長不得逾幾日?",
      "section": "乙、測驗題",
      "options": {
        "A": "15日",
        "B": "30日",
        "C": "40日",
        "D": "45日"
      },
      "answer": "C"
    },
    {
      "number": 15,
      "type": "choice",
      "stem": "依據民國 112 年 6 月 28 日修正公布之入出國及移民法,外國人於居留期間內居留原因消失者, 應廢止其居留許可。但下列那些情形,內政部移民署得准予其繼續居留? 1於離婚後對在臺灣地區已設有戶籍未成年子女,有撫育事實、行使負擔權利義務或會面交往 2為居住臺灣地區設有戶籍國民之配偶,因遭受家庭暴力離婚後再婚 3以配偶為依親對象,取得居留許可,其依親對象為我國國民,於離婚後 30 日內與原依親對 象再婚 4發生職業災害尚在治療中",
      "section": "乙、測驗題",
      "options": {
        "A": "123",
        "B": "124",
        "C": "134",
        "D": "234"
      },
      "answer": "C"
    },
    {
      "number": 16,
      "type": "choice",
      "stem": "依據民國 112 年 6 月 14 日修正公布之人口販運防制法,下列何者為「人口販運被害人屬我國籍 漁船經營者境外僱用非我國籍船員之勞動權益及其他必要協助事項」之中央目的事業主管機關?",
      "section": "乙、測驗題",
      "options": {
        "A": "海岸巡防主管機關",
        "B": "勞動主管機關",
        "C": "農業主管機關",
        "D": "法務主管機關"
      },
      "answer": "C"
    },
    {
      "number": 17,
      "type": "choice",
      "stem": "依據民國 112 年 6 月 28 日修正公布之入出國及移民法,下列何者非屬「外國人申請居留原因與 其原持憑入國之停留簽證目的相符,得向內政部移民署申請居留」之情形?",
      "section": "乙、測驗題",
      "options": {
        "A": "經海外聯合招生委員會許可在我國就學之僑生",
        "B": "經僑務主管機關核轉各級主管教育行政機關分發之自行回國就學僑生",
        "C": "經主管教育行政機關核定得招收外國學生之學校許可在我國就學之學生",
        "D": "經在教育部認可大專校院附設之華語教學機構就讀滿4個月,並繼續註冊3個月以上之學生"
      },
      "answer": "B"
    },
    {
      "number": 18,
      "type": "choice",
      "stem": "依據民國 112 年 6 月 28 日修正公布之入出國及移民法,取得居留許可之外國人,應於入國後之 翌日起算幾日內,向內政部移民署申請外僑居留證?",
      "section": "乙、測驗題",
      "options": {
        "A": "7日",
        "B": "15日",
        "C": "30日",
        "D": "60日"
      },
      "answer": "C"
    },
    {
      "number": 19,
      "type": "choice",
      "stem": "依據民國112年6月28日修正公布之入出國及移民法規定,下列有關入出國之規定,何者正確?",
      "section": "乙、測驗題",
      "options": {
        "A": "國民入出國皆須申請許可",
        "B": "國民或外國人入出國皆應經查驗",
        "C": "查驗時,應蒐集入出國者之指紋資料紀錄",
        "D": "各直轄市、縣(市)警察局因偵辦刑事案件,得通知內政部移民署禁止出國"
      },
      "answer": "B"
    },
    {
      "number": 20,
      "type": "choice",
      "stem": "司法院釋字第748號解釋施行法保障相同性別2人可向戶政機關辦理結婚登記,因涉外民事適用 法第 46 條規定婚姻成立的實質要件尚未修正,致不承認同婚國家之配偶不能辦理登記,惟內政 部民國 112 年 1 月 19 日有關跨國同性婚姻適用「涉外民事法律適用法」相關疑義函釋,放寬同 婚之戶籍登記,下列何者非該函釋內容?",
      "section": "乙、測驗題",
      "options": {
        "A": "依司法院釋字第 748 號解釋文以憲法第 22 條保障人民婚姻自由及第 7 條保障人民平等權之規 範,不得否定使相同性別2人,得為經營共同生活之目的,成立具有親密性及排他性之永久結 合關係,業已構成我國公共秩序之一部分",
        "B": "依適用涉外民事適用法第8條規定,例外不再適用該當事人不承認同性婚姻之本國法規定,以 消弭不平等待遇維護我國公共秩序,承認該當事人間之私法上同婚關係",
        "C": "兩岸同性伴侶結婚只要完備入境事由、面談機制及登記程序等整體行政管理措施後,即可 辦理登記",
        "D": "國人與港、澳地區人民依香港澳門關係條例第38條前段規定,民事事件,涉及香港或澳門者, 類推適用涉外民事法律適用法,亦可辦理登記"
      },
      "answer": "C"
    },
    {
      "number": 21,
      "type": "choice",
      "stem": "依據外國護照簽證條例規定,禮遇簽證不適用於下列何者?",
      "section": "乙、測驗題",
      "options": {
        "A": "外國卸任元首、副元首、總理、副總理、外交部長及其眷屬",
        "B": "外國政府派駐我國之人員及其眷屬、隨從",
        "C": "政府間國際組織之外國籍職員應我國政府邀請來訪者及其眷屬",
        "D": "應我國政府邀請或對我國有貢獻之外國人士及其眷屬"
      },
      "answer": "B"
    },
    {
      "number": 22,
      "type": "choice",
      "stem": "依據護照條例第19條之規定,下列那種情形,應申請換發護照?",
      "section": "乙、測驗題",
      "options": {
        "A": "護照所餘效期不足1年",
        "B": "所持護照非屬現行最新式樣",
        "C": "護照內植晶片無法讀取",
        "D": "持照人認有必要,並經主管機關同意"
      },
      "answer": "C"
    },
    {
      "number": 23,
      "type": "choice",
      "stem": "大陸地區人民經許可進入臺灣地區者,非在臺灣地區設有戶籍滿幾年,不得擔任情報機關(構) 人員,或國防機關(構)之志願役軍官、士官及士兵、義務役軍官及士官、文職、教職及國軍聘 雇人員?",
      "section": "乙、測驗題",
      "options": {
        "A": "5",
        "B": "10",
        "C": "15",
        "D": "20"
      },
      "answer": "D"
    },
    {
      "number": 24,
      "type": "choice",
      "stem": "依據民國112年就業服務法第58條修正條文規定,下列何者非修正內容?",
      "section": "乙、測驗題",
      "options": {
        "A": "外國人於聘僱許可有效期間,因不可歸責於雇主的原因出國、死亡或行蹤不明,依規定通知入 出國管理機關及警察機關滿3個月仍未查獲者,雇主得向中央主管機關申請遞補",
        "B": "外國人於雇主處所發生行蹤不明情事,依規定通知入出國管理機關及警察機關滿1個月仍未查 獲者,雇主得向中央主管機關申請遞補",
        "C": "產業移工與雇主合意轉換新雇主或工作,經中央主管機關廢止聘僱許可超過1個月未由新雇主 接續聘僱,雇主也可申請遞補新移工",
        "D": "家庭看護移工合意轉換雇主廢聘時,經中央主管機關廢止聘僱許可超過1個月未由新雇主接續 聘僱,雇主也可申請遞補新移工"
      },
      "answer": "C"
    },
    {
      "number": 25,
      "type": "choice",
      "stem": "中央研究院院士之資格條件依據該院之規定,須具有我國國籍。有關具有我國國籍認定之證明文 件,不含下列何者?",
      "section": "乙、測驗題",
      "options": {
        "A": "父母之一方具有我國國籍證明及本人出生證明",
        "B": "戶籍資料",
        "C": "僑務委員會依華裔證明文件核發華僑身分證明書",
        "D": "歸化國籍許可證書"
      },
      "answer": "C"
    }
  ],
  "year": 112,
  "category": "移民特考",
  "subject": "[三等] 入出國及移民法規(包括入出國及移民法、人口販運防制法、國籍法、就業服務法、臺灣地區與大陸地區人民關係條例、香港澳門關係條例、護照條例、外國護照簽證條例、涉外民事",
  "level": "三等",
  "original_subject": "入出國及移民法規（包括入出國及移民法、人口販運防制法、國籍法、就業服務法、臺灣地區與大陸地區人民關係條例、香港澳門關係條例、護照條例、外國護照簽證條例、涉外民事",
  "source_pdf": "/home/user/police-exam-archive/移民特考PDF/112年/三等/入出國及移民法規(包括入出國及移民法、人口販運防制法、國籍法、就業服務法、臺灣地區與大陸地區人民關係條例、香港澳門關係條例、護照條例、外國護照簽證條例、涉外民事/試題.pdf",
  "file_type": "試題",
  "total_questions": 27
}
